[
  {
    "jaText": "（走者・伊藤）二塁盗塁成功",
    "text": "Itoh steals 2nd base.",
    "countsAsStealAttempt": true,
    "catcher": {
        "id": "71375138",
        "jaBoxscoreName": "太田",
        "jaRegisteredName": "太田　光",
        "fullLFMName": "Ohta, Hikaru",
        "primaryNumber": "2",
        "teamCode": "E",
        "boxscoreName": "Ohta",
        "pitchHand": "R",
        "batSide": "R"
      }
  },
  {
    "jaText": "（走者・武岡）三塁盗塁成功",
    "text": "Takeoka steals 3rd base.",
    "countsAsStealAttempt": true,
    "catcher": {
        "id": "71375138",
        "jaBoxscoreName": "太田",
        "jaRegisteredName": "太田　光",
        "fullLFMName": "Ohta, Hikaru",
        "primaryNumber": "2",
        "teamCode": "E",
        "boxscoreName": "Ohta",
        "pitchHand": "R",
        "batSide": "R"
      }
  },
  {
    "jaText": "（走者・内山）二塁盗塁成功",
    "text": "Uchiyama steals 2nd base.",
    "countsAsStealAttempt": true,
    "catcher": {
        "id": "71375138",
        "jaBoxscoreName": "太田",
        "jaRegisteredName": "太田　光",
        "fullLFMName": "Ohta, Hikaru",
        "primaryNumber": "2",
        "teamCode": "E",
        "boxscoreName": "Ohta",
        "pitchHand": "R",
        "batSide": "R"
      }
  },
  {
    "jaText": "（走者・牧）二塁盗塁失敗",
    "text": "Maki caught stealing 2nd base.",
    "countsAsStealAttempt": true
  },
  {
    "jaText": "（走者・滝澤）二塁盗塁失敗",
    "text": "Takizawa caught stealing 2nd base.",
    "countsAsStealAttempt": true
  },
  {
    "jaText": "（走者・西川）二塁盗塁成功",
    "text": "Nishikawa steals 2nd base.",
    "countsAsStealAttempt": true,
    "catcher": {
        "id": "21125150",
        "jaBoxscoreName": "石伊",
        "jaRegisteredName": "石伊　雄太",
        "fullLFMName": "Ishii, Yuta",
        "primaryNumber": "9",
        "teamCode": "D",
        "boxscoreName": "Ishii",
        "pitchHand": "R",
        "batSide": "R"
      }
  },
  {
    "jaText": "（走者・近本）二塁盗塁成功",
    "text": "Chikamoto steals 2nd base.",
    "countsAsStealAttempt": true
  },
  {
    "jaText": "（走者・梅野）二塁盗塁失敗",
    "text": "Umeno caught stealing 2nd base.",
    "countsAsStealAttempt": true
  },
  {
    "jaText": "（走者・角中）二塁盗塁成功",
    "text": "Kakunaka steals 2nd base.",
    "countsAsStealAttempt": true,
    "catcher": {
        "id": "21325139",
        "jaBoxscoreName": "梅野",
        "jaRegisteredName": "梅野　隆太郎",
        "fullLFMName": "Umeno, Ryutaro",
        "primaryNumber": "2",
        "teamCode": "T",
        "boxscoreName": "Umeno",
        "pitchHand": "R",
        "batSide": "R"
      }
  },
  {
    "jaText": "（走者・野村）二塁盗塁成功",
    "text": "Nomura steals 2nd base.",
    "countsAsStealAttempt": true
  },
  {
    "jaText": "（走者・田中）二塁盗塁失敗",
    "text": "Tanaka caught stealing 2nd base.",
    "countsAsStealAttempt": true
  },
  {
    "jaText": "（走者・周東）二塁盗塁成功",
    "text": "Shuto steals 2nd base.",
    "countsAsStealAttempt": true
  }
]