{
  "records": [
    {
      "standingsType": "regular season",
      "season": "2025",
      "league": "Central League",
      "lastUpdated": "2025-08-08",
      "teamRecords": [
        {
          "teamName": "Tigers",
          "league": "Central",
          "wins": 61,
          "losses": 39,
          "ties": 2,
          "pct": ".610",
          "overall": {
            "gamesPlayed": 102,
            "wins": 61,
            "losses": 39,
            "ties": 2,
            "runsScored": 346,
            "runsAllowed": 233,
            "runDifferential": 113,
            "wlt": "WWLLTLWWWLLWLWWLLWWWWWWLLLLWWLWWLWWTLLWWWLLWLWWWLWWWWLWWWWLLLLLLLWWLWLLWWWWWWWWWWWLWWLLWWLWWWWLWWLWWLL",
            "streak": "L2",
            "splitRecords": [
              {
                "type": "left",
                "wins": 25,
                "losses": 20,
                "ties": 1
              },
              {
                "type": "right",
                "wins": 36,
                "losses": 19,
                "ties": 1
              },
              {
                "type": "oneRun",
                "wins": 17,
                "losses": 18
              },
              {
                "type": "shutout",
                "pitching": 23,
                "batting": 5,
                "ties": 0
              },
              {
                "type": "doubleDigitRuns",
                "scored": 1,
                "allowed": 0
              },
              {
                "type": "extraInning",
                "wins": 8,
                "losses": 7,
                "ties": 2
              },
              {
                "type": "walkoff",
                "wins": 3,
                "losses": 6
              },
              {
                "type": "comeback",
                "wins": 15,
                "losses": 18,
                "ties": 1
              },
              {
                "type": "firstRunScored",
                "wins": 47,
                "losses": 17,
                "ties": 0
              },
              {
                "type": "firstRunAllowed",
                "wins": 14,
                "losses": 22,
                "ties": 2
              },
              {
                "type": "xWinLoss",
                "wins": 67,
                "losses": 33,
                "luck": -6
              }
            ],
            "lastTen": {
              "wins": 6,
              "losses": 4,
              "ties": 0
            },
            "gamesBack": ""
          },
          "home": {
            "gamesPlayed": 50,
            "wins": 28,
            "losses": 21,
            "ties": 1,
            "runsScored": 150,
            "runsAllowed": 113,
            "runDifferential": 37,
            "wlt": "LTLLLWLLLWWWLWWLWWLWWWLLWWLWWWLWWLWLWWWLWWLLWWWWLL",
            "streak": "L2",
            "splitRecords": [
              {
                "type": "left",
                "wins": 13,
                "losses": 10,
                "ties": 0
              },
              {
                "type": "right",
                "wins": 15,
                "losses": 11,
                "ties": 1
              },
              {
                "type": "oneRun",
                "wins": 9,
                "losses": 7
              },
              {
                "type": "shutout",
                "pitching": 13,
                "batting": 3,
                "ties": 0
              },
              {
                "type": "doubleDigitRuns",
                "scored": 0,
                "allowed": 0
              },
              {
                "type": "extraInning",
                "wins": 2,
                "losses": 4,
                "ties": 1
              },
              {
                "type": "walkoff",
                "wins": 3,
                "losses": 0
              },
              {
                "type": "comeback",
                "wins": 6,
                "losses": 9,
                "ties": 1
              },
              {
                "type": "firstRunScored",
                "wins": 22,
                "losses": 8,
                "ties": 0
              },
              {
                "type": "firstRunAllowed",
                "wins": 6,
                "losses": 13,
                "ties": 1
              },
              {
                "type": "xWinLoss",
                "wins": 31,
                "losses": 18,
                "luck": -3
              }
            ],
            "lastTen": {
              "wins": 6,
              "losses": 4,
              "ties": 0
            }
          },
          "road": {
            "gamesPlayed": 52,
            "wins": 33,
            "losses": 18,
            "ties": 1,
            "runsScored": 196,
            "runsAllowed": 120,
            "runDifferential": 76,
            "wlt": "WWLWWWWWWWWLLLWWLTLWLWWWWWLWLLLLLLLWWWWWWWWWWLWWLWWL",
            "streak": "L1",
            "splitRecords": [
              {
                "type": "left",
                "wins": 12,
                "losses": 10,
                "ties": 1
              },
              {
                "type": "right",
                "wins": 21,
                "losses": 8,
                "ties": 0
              },
              {
                "type": "oneRun",
                "wins": 8,
                "losses": 11
              },
              {
                "type": "shutout",
                "pitching": 10,
                "batting": 2,
                "ties": 0
              },
              {
                "type": "doubleDigitRuns",
                "scored": 1,
                "allowed": 0
              },
              {
                "type": "extraInning",
                "wins": 6,
                "losses": 3,
                "ties": 1
              },
              {
                "type": "walkoff",
                "wins": 0,
                "losses": 6
              },
              {
                "type": "comeback",
                "wins": 9,
                "losses": 9,
                "ties": 0
              },
              {
                "type": "firstRunScored",
                "wins": 25,
                "losses": 9,
                "ties": 0
              },
              {
                "type": "firstRunAllowed",
                "wins": 8,
                "losses": 9,
                "ties": 1
              },
              {
                "type": "xWinLoss",
                "wins": 36,
                "losses": 15,
                "luck": -3
              }
            ],
            "lastTen": {
              "wins": 7,
              "losses": 3,
              "ties": 0
            }
          },
          "lastUpdated": "2025-08-08"
        },
        {
          "teamName": "Giants",
          "league": "Central",
          "wins": 49,
          "losses": 49,
          "ties": 3,
          "pct": ".500",
          "overall": {
            "gamesPlayed": 101,
            "wins": 49,
            "losses": 49,
            "ties": 3,
            "runsScored": 299,
            "runsAllowed": 300,
            "runDifferential": -1,
            "wlt": "WWWLWWLLLTWLLLWWLWWLWWLLWWWWLWLLWLWLLLLWWLLWWWWWLWWLLLLLWWLWTLLLLWLWWLLWWWLLLWTLWLWWLLLLWWWLWLLLWWWLW",
            "streak": "W1",
            "splitRecords": [
              {
                "type": "left",
                "wins": 19,
                "losses": 22,
                "ties": 2
              },
              {
                "type": "right",
                "wins": 30,
                "losses": 27,
                "ties": 1
              },
              {
                "type": "oneRun",
                "wins": 18,
                "losses": 21
              },
              {
                "type": "shutout",
                "pitching": 20,
                "batting": 11,
                "ties": 2
              },
              {
                "type": "doubleDigitRuns",
                "scored": 2,
                "allowed": 2
              },
              {
                "type": "extraInning",
                "wins": 5,
                "losses": 6,
                "ties": 3
              },
              {
                "type": "walkoff",
                "wins": 6,
                "losses": 6
              },
              {
                "type": "comeback",
                "wins": 18,
                "losses": 21,
                "ties": 0
              },
              {
                "type": "firstRunScored",
                "wins": 34,
                "losses": 18,
                "ties": 1
              },
              {
                "type": "firstRunAllowed",
                "wins": 15,
                "losses": 31,
                "ties": 2
              },
              {
                "type": "xWinLoss",
                "wins": 49,
                "losses": 49,
                "luck": 0
              }
            ],
            "lastTen": {
              "wins": 5,
              "losses": 5,
              "ties": 0
            },
            "gamesBack": "11.0"
          },
          "home": {
            "gamesPlayed": 51,
            "wins": 31,
            "losses": 19,
            "ties": 1,
            "runsScored": 153,
            "runsAllowed": 132,
            "runDifferential": 21,
            "wlt": "WWWLLLWWLWWWWWLLWWWLWWWLWLWWLWLWWLWWWWTLWLLLWLLWWWL",
            "streak": "L1",
            "splitRecords": [
              {
                "type": "left",
                "wins": 11,
                "losses": 10,
                "ties": 1
              },
              {
                "type": "right",
                "wins": 20,
                "losses": 9,
                "ties": 0
              },
              {
                "type": "oneRun",
                "wins": 12,
                "losses": 7
              },
              {
                "type": "shutout",
                "pitching": 16,
                "batting": 5,
                "ties": 1
              },
              {
                "type": "doubleDigitRuns",
                "scored": 1,
                "allowed": 1
              },
              {
                "type": "extraInning",
                "wins": 3,
                "losses": 1,
                "ties": 1
              },
              {
                "type": "walkoff",
                "wins": 6,
                "losses": 0
              },
              {
                "type": "comeback",
                "wins": 12,
                "losses": 6,
                "ties": 0
              },
              {
                "type": "firstRunScored",
                "wins": 21,
                "losses": 5,
                "ties": 1
              },
              {
                "type": "firstRunAllowed",
                "wins": 10,
                "losses": 14,
                "ties": 0
              },
              {
                "type": "xWinLoss",
                "wins": 28,
                "losses": 22,
                "luck": 3
              }
            ],
            "lastTen": {
              "wins": 4,
              "losses": 6,
              "ties": 0
            }
          },
          "road": {
            "gamesPlayed": 50,
            "wins": 18,
            "losses": 30,
            "ties": 2,
            "runsScored": 146,
            "runsAllowed": 168,
            "runDifferential": -22,
            "wlt": "LWWTWLLLWWLLLWLWLWLLLLLWWWLLLLLWTLLLLLLLWWLLWWLWLW",
            "streak": "W1",
            "splitRecords": [
              {
                "type": "left",
                "wins": 8,
                "losses": 12,
                "ties": 1
              },
              {
                "type": "right",
                "wins": 10,
                "losses": 18,
                "ties": 1
              },
              {
                "type": "oneRun",
                "wins": 6,
                "losses": 14
              },
              {
                "type": "shutout",
                "pitching": 4,
                "batting": 6,
                "ties": 1
              },
              {
                "type": "doubleDigitRuns",
                "scored": 1,
                "allowed": 1
              },
              {
                "type": "extraInning",
                "wins": 2,
                "losses": 5,
                "ties": 2
              },
              {
                "type": "walkoff",
                "wins": 0,
                "losses": 6
              },
              {
                "type": "comeback",
                "wins": 6,
                "losses": 15,
                "ties": 0
              },
              {
                "type": "firstRunScored",
                "wins": 13,
                "losses": 13,
                "ties": 0
              },
              {
                "type": "firstRunAllowed",
                "wins": 5,
                "losses": 17,
                "ties": 2
              },
              {
                "type": "xWinLoss",
                "wins": 21,
                "losses": 27,
                "luck": -3
              }
            ],
            "lastTen": {
              "wins": 6,
              "losses": 4,
              "ties": 0
            }
          },
          "lastUpdated": "2025-08-08"
        },
        {
          "teamName": "Baystars",
          "league": "Central",
          "wins": 46,
          "losses": 49,
          "ties": 5,
          "pct": ".484",
          "overall": {
            "gamesPlayed": 100,
            "wins": 46,
            "losses": 49,
            "ties": 5,
            "runsScored": 320,
            "runsAllowed": 307,
            "runDifferential": 13,
            "wlt": "WLWWTWLLLTLWLLWLLLLLWWWWLWWLWWLWLWTWWLWWLWWLLLWWWWWLWWLWLWLLLLLWLLWLLLLWWWLLLWTLLWWLTLWWLLLLWWWLWLWL",
            "streak": "L1",
            "splitRecords": [
              {
                "type": "left",
                "wins": 19,
                "losses": 22,
                "ties": 2
              },
              {
                "type": "right",
                "wins": 27,
                "losses": 27,
                "ties": 3
              },
              {
                "type": "oneRun",
                "wins": 18,
                "losses": 19
              },
              {
                "type": "shutout",
                "pitching": 13,
                "batting": 16,
                "ties": 0
              },
              {
                "type": "doubleDigitRuns",
                "scored": 3,
                "allowed": 2
              },
              {
                "type": "extraInning",
                "wins": 4,
                "losses": 4,
                "ties": 4
              },
              {
                "type": "walkoff",
                "wins": 3,
                "losses": 3
              },
              {
                "type": "comeback",
                "wins": 17,
                "losses": 11,
                "ties": 2
              },
              {
                "type": "firstRunScored",
                "wins": 33,
                "losses": 9,
                "ties": 3
              },
              {
                "type": "firstRunAllowed",
                "wins": 13,
                "losses": 40,
                "ties": 2
              },
              {
                "type": "xWinLoss",
                "wins": 49,
                "losses": 46,
                "luck": -3
              }
            ],
            "lastTen": {
              "wins": 5,
              "losses": 5,
              "ties": 0
            },
            "gamesBack": "12.5"
          },
          "home": {
            "gamesPlayed": 50,
            "wins": 26,
            "losses": 22,
            "ties": 2,
            "runsScored": 168,
            "runsAllowed": 161,
            "runDifferential": 7,
            "wlt": "WLWTLWLLLWWWWLWLWTWWLWWWWWLWLWLLWLWWWLLLLLWLLWWLWL",
            "streak": "L1",
            "splitRecords": [
              {
                "type": "left",
                "wins": 11,
                "losses": 9,
                "ties": 1
              },
              {
                "type": "right",
                "wins": 15,
                "losses": 13,
                "ties": 1
              },
              {
                "type": "oneRun",
                "wins": 14,
                "losses": 7
              },
              {
                "type": "shutout",
                "pitching": 6,
                "batting": 4,
                "ties": 0
              },
              {
                "type": "doubleDigitRuns",
                "scored": 2,
                "allowed": 2
              },
              {
                "type": "extraInning",
                "wins": 2,
                "losses": 2,
                "ties": 2
              },
              {
                "type": "walkoff",
                "wins": 3,
                "losses": 0
              },
              {
                "type": "comeback",
                "wins": 10,
                "losses": 4,
                "ties": 0
              },
              {
                "type": "firstRunScored",
                "wins": 19,
                "losses": 4,
                "ties": 2
              },
              {
                "type": "firstRunAllowed",
                "wins": 7,
                "losses": 18,
                "ties": 0
              },
              {
                "type": "xWinLoss",
                "wins": 25,
                "losses": 23,
                "luck": 1
              }
            ],
            "lastTen": {
              "wins": 4,
              "losses": 6,
              "ties": 0
            }
          },
          "road": {
            "gamesPlayed": 50,
            "wins": 20,
            "losses": 27,
            "ties": 3,
            "runsScored": 152,
            "runsAllowed": 146,
            "runDifferential": 6,
            "wlt": "WTWLLLLLWLLWLWWWLWLWWLLLWWLWLWLLLLLLLWTWLTLWWLLWWL",
            "streak": "L1",
            "splitRecords": [
              {
                "type": "left",
                "wins": 8,
                "losses": 13,
                "ties": 1
              },
              {
                "type": "right",
                "wins": 12,
                "losses": 14,
                "ties": 2
              },
              {
                "type": "oneRun",
                "wins": 4,
                "losses": 12
              },
              {
                "type": "shutout",
                "pitching": 7,
                "batting": 12,
                "ties": 0
              },
              {
                "type": "doubleDigitRuns",
                "scored": 1,
                "allowed": 0
              },
              {
                "type": "extraInning",
                "wins": 2,
                "losses": 2,
                "ties": 2
              },
              {
                "type": "walkoff",
                "wins": 0,
                "losses": 3
              },
              {
                "type": "comeback",
                "wins": 7,
                "losses": 7,
                "ties": 2
              },
              {
                "type": "firstRunScored",
                "wins": 14,
                "losses": 5,
                "ties": 1
              },
              {
                "type": "firstRunAllowed",
                "wins": 6,
                "losses": 22,
                "ties": 2
              },
              {
                "type": "xWinLoss",
                "wins": 24,
                "losses": 23,
                "luck": -4
              }
            ],
            "lastTen": {
              "wins": 4,
              "losses": 5,
              "ties": 1
            }
          },
          "lastUpdated": "2025-08-08"
        },
        {
          "teamName": "Carp",
          "league": "Central",
          "wins": 43,
          "losses": 52,
          "ties": 5,
          "pct": ".453",
          "overall": {
            "gamesPlayed": 100,
            "wins": 43,
            "losses": 52,
            "ties": 5,
            "runsScored": 302,
            "runsAllowed": 324,
            "runDifferential": -22,
            "wlt": "LLWLLWWWTLWWWWWLWWLWLLLLLLLWWWWLWLWWWWLLWTLWWLLLLWLLWWWLWLWLLLWLLWWLWWTWLLTWLLLLLLLWTLLLLLLLWWLWLWLW",
            "streak": "W1",
            "splitRecords": [
              {
                "type": "left",
                "wins": 21,
                "losses": 25,
                "ties": 3
              },
              {
                "type": "right",
                "wins": 22,
                "losses": 27,
                "ties": 2
              },
              {
                "type": "oneRun",
                "wins": 15,
                "losses": 21
              },
              {
                "type": "shutout",
                "pitching": 9,
                "batting": 17,
                "ties": 1
              },
              {
                "type": "doubleDigitRuns",
                "scored": 2,
                "allowed": 1
              },
              {
                "type": "extraInning",
                "wins": 5,
                "losses": 6,
                "ties": 4
              },
              {
                "type": "walkoff",
                "wins": 2,
                "losses": 8
              },
              {
                "type": "comeback",
                "wins": 17,
                "losses": 19,
                "ties": 0
              },
              {
                "type": "firstRunScored",
                "wins": 26,
                "losses": 13,
                "ties": 1
              },
              {
                "type": "firstRunAllowed",
                "wins": 17,
                "losses": 39,
                "ties": 4
              },
              {
                "type": "xWinLoss",
                "wins": 44,
                "losses": 51,
                "luck": -1
              }
            ],
            "lastTen": {
              "wins": 5,
              "losses": 5,
              "ties": 0
            },
            "gamesBack": "15.5"
          },
          "home": {
            "gamesPlayed": 48,
            "wins": 26,
            "losses": 19,
            "ties": 3,
            "runsScored": 162,
            "runsAllowed": 148,
            "runDifferential": 14,
            "wlt": "LLWWWWWWWWLWLWWWWWWTLWLLLWWWLWLLWWTWLLLLLWTLLWLW",
            "streak": "W1",
            "splitRecords": [
              {
                "type": "left",
                "wins": 14,
                "losses": 9,
                "ties": 1
              },
              {
                "type": "right",
                "wins": 12,
                "losses": 10,
                "ties": 2
              },
              {
                "type": "oneRun",
                "wins": 9,
                "losses": 4
              },
              {
                "type": "shutout",
                "pitching": 6,
                "batting": 9,
                "ties": 0
              },
              {
                "type": "doubleDigitRuns",
                "scored": 2,
                "allowed": 1
              },
              {
                "type": "extraInning",
                "wins": 2,
                "losses": 0,
                "ties": 2
              },
              {
                "type": "walkoff",
                "wins": 2,
                "losses": 0
              },
              {
                "type": "comeback",
                "wins": 11,
                "losses": 5,
                "ties": 0
              },
              {
                "type": "firstRunScored",
                "wins": 15,
                "losses": 4,
                "ties": 1
              },
              {
                "type": "firstRunAllowed",
                "wins": 11,
                "losses": 15,
                "ties": 2
              },
              {
                "type": "xWinLoss",
                "wins": 24,
                "losses": 21,
                "luck": 2
              }
            ],
            "lastTen": {
              "wins": 3,
              "losses": 6,
              "ties": 1
            }
          },
          "road": {
            "gamesPlayed": 52,
            "wins": 17,
            "losses": 33,
            "ties": 2,
            "runsScored": 140,
            "runsAllowed": 176,
            "runDifferential": -36,
            "wlt": "LLTLWWWLLLLLLLWWLWLWLLWLWLLLWLWLLLWWLTWLLLLLLLLWLWLW",
            "streak": "W1",
            "splitRecords": [
              {
                "type": "left",
                "wins": 7,
                "losses": 16,
                "ties": 2
              },
              {
                "type": "right",
                "wins": 10,
                "losses": 17,
                "ties": 0
              },
              {
                "type": "oneRun",
                "wins": 6,
                "losses": 17
              },
              {
                "type": "shutout",
                "pitching": 3,
                "batting": 8,
                "ties": 1
              },
              {
                "type": "doubleDigitRuns",
                "scored": 0,
                "allowed": 0
              },
              {
                "type": "extraInning",
                "wins": 3,
                "losses": 6,
                "ties": 2
              },
              {
                "type": "walkoff",
                "wins": 0,
                "losses": 8
              },
              {
                "type": "comeback",
                "wins": 6,
                "losses": 14,
                "ties": 0
              },
              {
                "type": "firstRunScored",
                "wins": 11,
                "losses": 9,
                "ties": 0
              },
              {
                "type": "firstRunAllowed",
                "wins": 6,
                "losses": 24,
                "ties": 2
              },
              {
                "type": "xWinLoss",
                "wins": 20,
                "losses": 30,
                "luck": -3
              }
            ],
            "lastTen": {
              "wins": 3,
              "losses": 7,
              "ties": 0
            }
          },
          "lastUpdated": "2025-08-08"
        },
        {
          "teamName": "Dragons",
          "league": "Central",
          "wins": 44,
          "losses": 54,
          "ties": 2,
          "pct": ".449",
          "overall": {
            "gamesPlayed": 100,
            "wins": 44,
            "losses": 54,
            "ties": 2,
            "runsScored": 268,
            "runsAllowed": 302,
            "runDifferential": -34,
            "wlt": "LWLWLLTLWTWLLWLWWWLLLWLWWWWLLLLWLLWWLLWLWLLWLLWWLWWLLLWWWWWLWLLLWLLLWWLLLLLWLLLWWWWWWWLLLLWLWLWLLLWL",
            "streak": "L1",
            "splitRecords": [
              {
                "type": "left",
                "wins": 13,
                "losses": 23,
                "ties": 0
              },
              {
                "type": "right",
                "wins": 31,
                "losses": 31,
                "ties": 2
              },
              {
                "type": "oneRun",
                "wins": 21,
                "losses": 22
              },
              {
                "type": "shutout",
                "pitching": 8,
                "batting": 17,
                "ties": 0
              },
              {
                "type": "doubleDigitRuns",
                "scored": 0,
                "allowed": 1
              },
              {
                "type": "extraInning",
                "wins": 5,
                "losses": 6,
                "ties": 2
              },
              {
                "type": "walkoff",
                "wins": 4,
                "losses": 1
              },
              {
                "type": "comeback",
                "wins": 18,
                "losses": 20,
                "ties": 0
              },
              {
                "type": "firstRunScored",
                "wins": 31,
                "losses": 17,
                "ties": 2
              },
              {
                "type": "firstRunAllowed",
                "wins": 13,
                "losses": 37,
                "ties": 0
              },
              {
                "type": "xWinLoss",
                "wins": 44,
                "losses": 54,
                "luck": 0
              }
            ],
            "lastTen": {
              "wins": 4,
              "losses": 6,
              "ties": 0
            },
            "gamesBack": "16.0"
          },
          "home": {
            "gamesPlayed": 53,
            "wins": 28,
            "losses": 24,
            "ties": 1,
            "runsScored": 156,
            "runsAllowed": 147,
            "runDifferential": 9,
            "wlt": "WLLTWLWWLWLWWWLLWWWLWLLWWWWWLWLLLWWLLWLLWWWWLLWLWLLWL",
            "streak": "L1",
            "splitRecords": [
              {
                "type": "left",
                "wins": 11,
                "losses": 11,
                "ties": 0
              },
              {
                "type": "right",
                "wins": 17,
                "losses": 13,
                "ties": 1
              },
              {
                "type": "oneRun",
                "wins": 14,
                "losses": 10
              },
              {
                "type": "shutout",
                "pitching": 3,
                "batting": 6,
                "ties": 0
              },
              {
                "type": "doubleDigitRuns",
                "scored": 0,
                "allowed": 0
              },
              {
                "type": "extraInning",
                "wins": 3,
                "losses": 6,
                "ties": 1
              },
              {
                "type": "walkoff",
                "wins": 4,
                "losses": 0
              },
              {
                "type": "comeback",
                "wins": 11,
                "losses": 11,
                "ties": 0
              },
              {
                "type": "firstRunScored",
                "wins": 20,
                "losses": 10,
                "ties": 1
              },
              {
                "type": "firstRunAllowed",
                "wins": 8,
                "losses": 14,
                "ties": 0
              },
              {
                "type": "xWinLoss",
                "wins": 27,
                "losses": 25,
                "luck": 1
              }
            ],
            "lastTen": {
              "wins": 4,
              "losses": 6,
              "ties": 0
            }
          },
          "road": {
            "gamesPlayed": 47,
            "wins": 16,
            "losses": 30,
            "ties": 1,
            "runsScored": 112,
            "runsAllowed": 155,
            "runDifferential": -43,
            "wlt": "LWLTLWLWLWLLWLLLLLLWLWLLWWLLLWWLWLLLLLLWWWLLLWL",
            "streak": "L1",
            "splitRecords": [
              {
                "type": "left",
                "wins": 2,
                "losses": 12,
                "ties": 0
              },
              {
                "type": "right",
                "wins": 14,
                "losses": 18,
                "ties": 1
              },
              {
                "type": "oneRun",
                "wins": 7,
                "losses": 12
              },
              {
                "type": "shutout",
                "pitching": 5,
                "batting": 11,
                "ties": 0
              },
              {
                "type": "doubleDigitRuns",
                "scored": 0,
                "allowed": 1
              },
              {
                "type": "extraInning",
                "wins": 2,
                "losses": 0,
                "ties": 1
              },
              {
                "type": "walkoff",
                "wins": 0,
                "losses": 1
              },
              {
                "type": "comeback",
                "wins": 7,
                "losses": 9,
                "ties": 0
              },
              {
                "type": "firstRunScored",
                "wins": 11,
                "losses": 7,
                "ties": 1
              },
              {
                "type": "firstRunAllowed",
                "wins": 5,
                "losses": 23,
                "ties": 0
              },
              {
                "type": "xWinLoss",
                "wins": 16,
                "losses": 30,
                "luck": 0
              }
            ],
            "lastTen": {
              "wins": 4,
              "losses": 6,
              "ties": 0
            }
          },
          "lastUpdated": "2025-08-08"
        },
        {
          "teamName": "Swallows",
          "league": "Central",
          "wins": 35,
          "losses": 55,
          "ties": 5,
          "pct": ".389",
          "overall": {
            "gamesPlayed": 95,
            "wins": 35,
            "losses": 55,
            "ties": 5,
            "runsScored": 263,
            "runsAllowed": 369,
            "runDifferential": -106,
            "wlt": "LLLWWTWLWWLLLLLWLWLWLWLLLWLLWLWLLLWLLTLLLWLLLLLLLWWLWLLLLWLTLLLWLWLLTLWLWWLTWLLWWWWWWWWLLLWLLWW",
            "streak": "W2",
            "splitRecords": [
              {
                "type": "left",
                "wins": 16,
                "losses": 21,
                "ties": 1
              },
              {
                "type": "right",
                "wins": 19,
                "losses": 34,
                "ties": 4
              },
              {
                "type": "oneRun",
                "wins": 16,
                "losses": 14
              },
              {
                "type": "shutout",
                "pitching": 5,
                "batting": 13,
                "ties": 0
              },
              {
                "type": "doubleDigitRuns",
                "scored": 0,
                "allowed": 4
              },
              {
                "type": "extraInning",
                "wins": 5,
                "losses": 6,
                "ties": 5
              },
              {
                "type": "walkoff",
                "wins": 5,
                "losses": 4
              },
              {
                "type": "comeback",
                "wins": 18,
                "losses": 15,
                "ties": 2
              },
              {
                "type": "firstRunScored",
                "wins": 21,
                "losses": 12,
                "ties": 3
              },
              {
                "type": "firstRunAllowed",
                "wins": 14,
                "losses": 43,
                "ties": 2
              },
              {
                "type": "xWinLoss",
                "wins": 31,
                "losses": 59,
                "luck": 4
              }
            ],
            "lastTen": {
              "wins": 5,
              "losses": 5,
              "ties": 0
            },
            "gamesBack": "21.0"
          },
          "home": {
            "gamesPlayed": 47,
            "wins": 20,
            "losses": 24,
            "ties": 3,
            "runsScored": 141,
            "runsAllowed": 186,
            "runDifferential": -45,
            "wlt": "WWTWLLLLLWLWLLLWLWLWLWLLWLWTLLLWLWLLLTWWWWWWLLW",
            "streak": "W1",
            "splitRecords": [
              {
                "type": "left",
                "wins": 9,
                "losses": 10,
                "ties": 0
              },
              {
                "type": "right",
                "wins": 11,
                "losses": 14,
                "ties": 3
              },
              {
                "type": "oneRun",
                "wins": 12,
                "losses": 3
              },
              {
                "type": "shutout",
                "pitching": 2,
                "batting": 6,
                "ties": 0
              },
              {
                "type": "doubleDigitRuns",
                "scored": 0,
                "allowed": 2
              },
              {
                "type": "extraInning",
                "wins": 3,
                "losses": 4,
                "ties": 3
              },
              {
                "type": "walkoff",
                "wins": 5,
                "losses": 0
              },
              {
                "type": "comeback",
                "wins": 11,
                "losses": 5,
                "ties": 2
              },
              {
                "type": "firstRunScored",
                "wins": 12,
                "losses": 3,
                "ties": 1
              },
              {
                "type": "firstRunAllowed",
                "wins": 8,
                "losses": 21,
                "ties": 2
              },
              {
                "type": "xWinLoss",
                "wins": 17,
                "losses": 27,
                "luck": 3
              }
            ],
            "lastTen": {
              "wins": 7,
              "losses": 2,
              "ties": 1
            }
          },
          "road": {
            "gamesPlayed": 48,
            "wins": 15,
            "losses": 31,
            "ties": 2,
            "runsScored": 122,
            "runsAllowed": 183,
            "runDifferential": -61,
            "wlt": "LLLWWLLWLWLLWLLLTLLLLLLLLWLLLLWLTLWLWWWLLWWLLLWW",
            "streak": "W2",
            "splitRecords": [
              {
                "type": "left",
                "wins": 7,
                "losses": 11,
                "ties": 1
              },
              {
                "type": "right",
                "wins": 8,
                "losses": 20,
                "ties": 1
              },
              {
                "type": "oneRun",
                "wins": 4,
                "losses": 11
              },
              {
                "type": "shutout",
                "pitching": 3,
                "batting": 7,
                "ties": 0
              },
              {
                "type": "doubleDigitRuns",
                "scored": 0,
                "allowed": 2
              },
              {
                "type": "extraInning",
                "wins": 2,
                "losses": 2,
                "ties": 2
              },
              {
                "type": "walkoff",
                "wins": 0,
                "losses": 4
              },
              {
                "type": "comeback",
                "wins": 7,
                "losses": 10,
                "ties": 0
              },
              {
                "type": "firstRunScored",
                "wins": 9,
                "losses": 9,
                "ties": 2
              },
              {
                "type": "firstRunAllowed",
                "wins": 6,
                "losses": 22,
                "ties": 0
              },
              {
                "type": "xWinLoss",
                "wins": 15,
                "losses": 31,
                "luck": 0
              }
            ],
            "lastTen": {
              "wins": 5,
              "losses": 5,
              "ties": 0
            }
          },
          "lastUpdated": "2025-08-08"
        }
      ]
    },
    {
      "standingsType": "regular season",
      "season": "2025",
      "league": "Pacific League",
      "lastUpdated": "2025-08-07",
      "teamRecords": [
        {
          "teamName": "Hawks",
          "league": "Pacific",
          "wins": 60,
          "losses": 36,
          "ties": 4,
          "pct": ".625",
          "overall": {
            "gamesPlayed": 100,
            "wins": 60,
            "losses": 36,
            "ties": 4,
            "runsScored": 386,
            "runsAllowed": 272,
            "runDifferential": 114,
            "wlt": "LLLWLLLWWWTWWLLLLLWTWWLLLLLWWWWWLWLWWLWLWWWLWLLWWLWWWLWLWLTWWWWLWWLWWLWWWWLWWWWLLLWWWTWWWWWWLWWWWLWW",
            "streak": "W2",
            "splitRecords": [
              {
                "type": "left",
                "wins": 25,
                "losses": 15,
                "ties": 1
              },
              {
                "type": "right",
                "wins": 35,
                "losses": 21,
                "ties": 3
              },
              {
                "type": "oneRun",
                "wins": 17,
                "losses": 12
              },
              {
                "type": "shutout",
                "pitching": 14,
                "batting": 10,
                "ties": 1
              },
              {
                "type": "doubleDigitRuns",
                "scored": 8,
                "allowed": 1
              },
              {
                "type": "extraInning",
                "wins": 4,
                "losses": 5,
                "ties": 3
              },
              {
                "type": "walkoff",
                "wins": 4,
                "losses": 3
              },
              {
                "type": "comeback",
                "wins": 19,
                "losses": 12,
                "ties": 0
              },
              {
                "type": "firstRunScored",
                "wins": 44,
                "losses": 10,
                "ties": 2
              },
              {
                "type": "firstRunAllowed",
                "wins": 16,
                "losses": 26,
                "ties": 2
              },
              {
                "type": "xWinLoss",
                "wins": 63,
                "losses": 33,
                "luck": -3
              }
            ],
            "lastTen": {
              "wins": 8,
              "losses": 2,
              "ties": 0
            },
            "gamesBack": ""
          },
          "home": {
            "gamesPlayed": 49,
            "wins": 29,
            "losses": 17,
            "ties": 3,
            "runsScored": 187,
            "runsAllowed": 137,
            "runDifferential": 50,
            "wlt": "LLLLLWLLLTWLLLWWWWLWLWWLLWWWWWLTWWWWWWLWWWWTWWWWW",
            "streak": "W9",
            "splitRecords": [
              {
                "type": "left",
                "wins": 14,
                "losses": 8,
                "ties": 1
              },
              {
                "type": "right",
                "wins": 15,
                "losses": 9,
                "ties": 2
              },
              {
                "type": "oneRun",
                "wins": 8,
                "losses": 6
              },
              {
                "type": "shutout",
                "pitching": 7,
                "batting": 3,
                "ties": 1
              },
              {
                "type": "doubleDigitRuns",
                "scored": 3,
                "allowed": 1
              },
              {
                "type": "extraInning",
                "wins": 1,
                "losses": 3,
                "ties": 2
              },
              {
                "type": "walkoff",
                "wins": 4,
                "losses": 0
              },
              {
                "type": "comeback",
                "wins": 10,
                "losses": 7,
                "ties": 0
              },
              {
                "type": "firstRunScored",
                "wins": 21,
                "losses": 6,
                "ties": 1
              },
              {
                "type": "firstRunAllowed",
                "wins": 8,
                "losses": 11,
                "ties": 2
              },
              {
                "type": "xWinLoss",
                "wins": 29,
                "losses": 17,
                "luck": 0
              }
            ],
            "lastTen": {
              "wins": 9,
              "losses": 0,
              "ties": 1
            }
          },
          "road": {
            "gamesPlayed": 51,
            "wins": 31,
            "losses": 19,
            "ties": 1,
            "runsScored": 199,
            "runsAllowed": 135,
            "runDifferential": 64,
            "wlt": "WLWWTWWLLWWLLWWLWLWWLWWLLWLWLWWLWWLWWWLLLWWWWWLWLWW",
            "streak": "W2",
            "splitRecords": [
              {
                "type": "left",
                "wins": 11,
                "losses": 7,
                "ties": 0
              },
              {
                "type": "right",
                "wins": 20,
                "losses": 12,
                "ties": 1
              },
              {
                "type": "oneRun",
                "wins": 9,
                "losses": 6
              },
              {
                "type": "shutout",
                "pitching": 7,
                "batting": 7,
                "ties": 0
              },
              {
                "type": "doubleDigitRuns",
                "scored": 5,
                "allowed": 0
              },
              {
                "type": "extraInning",
                "wins": 3,
                "losses": 2,
                "ties": 1
              },
              {
                "type": "walkoff",
                "wins": 0,
                "losses": 3
              },
              {
                "type": "comeback",
                "wins": 9,
                "losses": 5,
                "ties": 0
              },
              {
                "type": "firstRunScored",
                "wins": 23,
                "losses": 4,
                "ties": 1
              },
              {
                "type": "firstRunAllowed",
                "wins": 8,
                "losses": 15,
                "ties": 0
              },
              {
                "type": "xWinLoss",
                "wins": 34,
                "losses": 16,
                "luck": -3
              }
            ],
            "lastTen": {
              "wins": 8,
              "losses": 2,
              "ties": 0
            }
          },
          "lastUpdated": "2025-08-07"
        },
        {
          "teamName": "Fighters",
          "league": "Pacific",
          "wins": 60,
          "losses": 38,
          "ties": 2,
          "pct": ".612",
          "overall": {
            "gamesPlayed": 100,
            "wins": 60,
            "losses": 38,
            "ties": 2,
            "runsScored": 380,
            "runsAllowed": 258,
            "runDifferential": 122,
            "wlt": "WWWLWLLLWWWWLLWLLWWLLLWLWWWLWLWTWWWWLWWLLWLWLTWLWWWLWLLWLWWWLWWWLWWWLWLWLLLWWWWWLWWWWLWWWWLLWLLWWWWL",
            "streak": "L1",
            "splitRecords": [
              {
                "type": "left",
                "wins": 22,
                "losses": 15,
                "ties": 1
              },
              {
                "type": "right",
                "wins": 38,
                "losses": 23,
                "ties": 1
              },
              {
                "type": "oneRun",
                "wins": 19,
                "losses": 20
              },
              {
                "type": "shutout",
                "pitching": 17,
                "batting": 6,
                "ties": 0
              },
              {
                "type": "doubleDigitRuns",
                "scored": 4,
                "allowed": 1
              },
              {
                "type": "extraInning",
                "wins": 5,
                "losses": 4,
                "ties": 2
              },
              {
                "type": "walkoff",
                "wins": 5,
                "losses": 6
              },
              {
                "type": "comeback",
                "wins": 16,
                "losses": 15,
                "ties": 0
              },
              {
                "type": "firstRunScored",
                "wins": 48,
                "losses": 13,
                "ties": 2
              },
              {
                "type": "firstRunAllowed",
                "wins": 12,
                "losses": 25,
                "ties": 0
              },
              {
                "type": "xWinLoss",
                "wins": 66,
                "losses": 32,
                "luck": -6
              }
            ],
            "lastTen": {
              "wins": 5,
              "losses": 5,
              "ties": 0
            },
            "gamesBack": "1.0"
          },
          "home": {
            "gamesPlayed": 50,
            "wins": 28,
            "losses": 22,
            "ties": 0,
            "runsScored": 189,
            "runsAllowed": 161,
            "runDifferential": 28,
            "wlt": "LWLLLWLLLLLWLLWWWWWLWLWLWWWLWLWWWLWWWWWLWWWLLWLWWL",
            "streak": "L1",
            "splitRecords": [
              {
                "type": "left",
                "wins": 12,
                "losses": 10,
                "ties": 0
              },
              {
                "type": "right",
                "wins": 16,
                "losses": 12,
                "ties": 0
              },
              {
                "type": "oneRun",
                "wins": 10,
                "losses": 8
              },
              {
                "type": "shutout",
                "pitching": 9,
                "batting": 3,
                "ties": 0
              },
              {
                "type": "doubleDigitRuns",
                "scored": 1,
                "allowed": 1
              },
              {
                "type": "extraInning",
                "wins": 2,
                "losses": 2,
                "ties": 0
              },
              {
                "type": "walkoff",
                "wins": 5,
                "losses": 0
              },
              {
                "type": "comeback",
                "wins": 9,
                "losses": 6,
                "ties": 0
              },
              {
                "type": "firstRunScored",
                "wins": 22,
                "losses": 5,
                "ties": 0
              },
              {
                "type": "firstRunAllowed",
                "wins": 6,
                "losses": 17,
                "ties": 0
              },
              {
                "type": "xWinLoss",
                "wins": 29,
                "losses": 21,
                "luck": -1
              }
            ],
            "lastTen": {
              "wins": 6,
              "losses": 4,
              "ties": 0
            }
          },
          "road": {
            "gamesPlayed": 50,
            "wins": 32,
            "losses": 16,
            "ties": 2,
            "runsScored": 191,
            "runsAllowed": 97,
            "runDifferential": 94,
            "wlt": "WWWWWWWLLWWWWWLWTWLWLTWLLWLWLWWWLWLWLLLWWWWLWWWLWW",
            "streak": "W2",
            "splitRecords": [
              {
                "type": "left",
                "wins": 10,
                "losses": 5,
                "ties": 1
              },
              {
                "type": "right",
                "wins": 22,
                "losses": 11,
                "ties": 1
              },
              {
                "type": "oneRun",
                "wins": 9,
                "losses": 12
              },
              {
                "type": "shutout",
                "pitching": 8,
                "batting": 3,
                "ties": 0
              },
              {
                "type": "doubleDigitRuns",
                "scored": 3,
                "allowed": 0
              },
              {
                "type": "extraInning",
                "wins": 3,
                "losses": 2,
                "ties": 2
              },
              {
                "type": "walkoff",
                "wins": 0,
                "losses": 6
              },
              {
                "type": "comeback",
                "wins": 7,
                "losses": 9,
                "ties": 0
              },
              {
                "type": "firstRunScored",
                "wins": 26,
                "losses": 8,
                "ties": 2
              },
              {
                "type": "firstRunAllowed",
                "wins": 6,
                "losses": 8,
                "ties": 0
              },
              {
                "type": "xWinLoss",
                "wins": 37,
                "losses": 11,
                "luck": -5
              }
            ],
            "lastTen": {
              "wins": 8,
              "losses": 2,
              "ties": 0
            }
          },
          "lastUpdated": "2025-08-07"
        },
        {
          "teamName": "Buffaloes",
          "league": "Pacific",
          "wins": 49,
          "losses": 46,
          "ties": 3,
          "pct": ".516",
          "overall": {
            "gamesPlayed": 98,
            "wins": 49,
            "losses": 46,
            "ties": 3,
            "runsScored": 338,
            "runsAllowed": 365,
            "runDifferential": -27,
            "wlt": "WLWWWWWWLLTWWWWLLWLLTLWLLWWWLWLTLWLLWLLLWWWLWLWWLLWWLLLWLWWWWWLWWLWWWLWWWLWLLWWLLLWWLLLLLLWWWLLLLL",
            "streak": "L5",
            "splitRecords": [
              {
                "type": "left",
                "wins": 17,
                "losses": 17,
                "ties": 3
              },
              {
                "type": "right",
                "wins": 32,
                "losses": 29,
                "ties": 0
              },
              {
                "type": "oneRun",
                "wins": 13,
                "losses": 12
              },
              {
                "type": "shutout",
                "pitching": 9,
                "batting": 14,
                "ties": 0
              },
              {
                "type": "doubleDigitRuns",
                "scored": 4,
                "allowed": 4
              },
              {
                "type": "extraInning",
                "wins": 6,
                "losses": 6,
                "ties": 3
              },
              {
                "type": "walkoff",
                "wins": 8,
                "losses": 4
              },
              {
                "type": "comeback",
                "wins": 16,
                "losses": 16,
                "ties": 0
              },
              {
                "type": "firstRunScored",
                "wins": 39,
                "losses": 13,
                "ties": 1
              },
              {
                "type": "firstRunAllowed",
                "wins": 10,
                "losses": 33,
                "ties": 2
              },
              {
                "type": "xWinLoss",
                "wins": 44,
                "losses": 51,
                "luck": 5
              }
            ],
            "lastTen": {
              "wins": 3,
              "losses": 7,
              "ties": 0
            },
            "gamesBack": "10.5"
          },
          "home": {
            "gamesPlayed": 51,
            "wins": 27,
            "losses": 22,
            "ties": 2,
            "runsScored": 170,
            "runsAllowed": 178,
            "runDifferential": -8,
            "wlt": "WLWLLTWLLWLLWWWLTLWLWWLWLLWWWLWWWWWWLWLWLLWLWLWWWLL",
            "streak": "L2",
            "splitRecords": [
              {
                "type": "left",
                "wins": 10,
                "losses": 9,
                "ties": 2
              },
              {
                "type": "right",
                "wins": 17,
                "losses": 13,
                "ties": 0
              },
              {
                "type": "oneRun",
                "wins": 9,
                "losses": 7
              },
              {
                "type": "shutout",
                "pitching": 6,
                "batting": 5,
                "ties": 0
              },
              {
                "type": "doubleDigitRuns",
                "scored": 1,
                "allowed": 2
              },
              {
                "type": "extraInning",
                "wins": 2,
                "losses": 3,
                "ties": 2
              },
              {
                "type": "walkoff",
                "wins": 8,
                "losses": 0
              },
              {
                "type": "comeback",
                "wins": 8,
                "losses": 8,
                "ties": 0
              },
              {
                "type": "firstRunScored",
                "wins": 22,
                "losses": 5,
                "ties": 0
              },
              {
                "type": "firstRunAllowed",
                "wins": 5,
                "losses": 17,
                "ties": 2
              },
              {
                "type": "xWinLoss",
                "wins": 23,
                "losses": 26,
                "luck": 4
              }
            ],
            "lastTen": {
              "wins": 5,
              "losses": 5,
              "ties": 0
            }
          },
          "road": {
            "gamesPlayed": 47,
            "wins": 22,
            "losses": 24,
            "ties": 1,
            "runsScored": 168,
            "runsAllowed": 187,
            "runDifferential": -19,
            "wlt": "WWWWWWWWTLWLLWLLWLLLWWLWLLLWLWWLWWWWLLWLLLLLLLL",
            "streak": "L8",
            "splitRecords": [
              {
                "type": "left",
                "wins": 7,
                "losses": 8,
                "ties": 1
              },
              {
                "type": "right",
                "wins": 15,
                "losses": 16,
                "ties": 0
              },
              {
                "type": "oneRun",
                "wins": 4,
                "losses": 5
              },
              {
                "type": "shutout",
                "pitching": 3,
                "batting": 9,
                "ties": 0
              },
              {
                "type": "doubleDigitRuns",
                "scored": 3,
                "allowed": 2
              },
              {
                "type": "extraInning",
                "wins": 4,
                "losses": 3,
                "ties": 1
              },
              {
                "type": "walkoff",
                "wins": 0,
                "losses": 4
              },
              {
                "type": "comeback",
                "wins": 8,
                "losses": 8,
                "ties": 0
              },
              {
                "type": "firstRunScored",
                "wins": 17,
                "losses": 8,
                "ties": 1
              },
              {
                "type": "firstRunAllowed",
                "wins": 5,
                "losses": 16,
                "ties": 0
              },
              {
                "type": "xWinLoss",
                "wins": 21,
                "losses": 25,
                "luck": 1
              }
            ],
            "lastTen": {
              "wins": 1,
              "losses": 9,
              "ties": 0
            }
          },
          "lastUpdated": "2025-08-07"
        },
        {
          "teamName": "Eagles",
          "league": "Pacific",
          "wins": 47,
          "losses": 49,
          "ties": 2,
          "pct": ".490",
          "overall": {
            "gamesPlayed": 98,
            "wins": 47,
            "losses": 49,
            "ties": 2,
            "runsScored": 282,
            "runsAllowed": 326,
            "runDifferential": -44,
            "wlt": "LWLWWLWLLLLLLWWWLWWWWLWWLLLLWWLLLLWWLWLLLWLWTWLWLWLWLWLLLLWWWWTWWWLLLLWWLLLLWWLWWLWLLLLWWWWWLLLWWW",
            "streak": "W3",
            "splitRecords": [
              {
                "type": "left",
                "wins": 18,
                "losses": 26,
                "ties": 1
              },
              {
                "type": "right",
                "wins": 29,
                "losses": 23,
                "ties": 1
              },
              {
                "type": "oneRun",
                "wins": 18,
                "losses": 11
              },
              {
                "type": "shutout",
                "pitching": 11,
                "batting": 13,
                "ties": 0
              },
              {
                "type": "doubleDigitRuns",
                "scored": 1,
                "allowed": 3
              },
              {
                "type": "extraInning",
                "wins": 7,
                "losses": 2,
                "ties": 2
              },
              {
                "type": "walkoff",
                "wins": 6,
                "losses": 4
              },
              {
                "type": "comeback",
                "wins": 14,
                "losses": 8,
                "ties": 1
              },
              {
                "type": "firstRunScored",
                "wins": 34,
                "losses": 7,
                "ties": 1
              },
              {
                "type": "firstRunAllowed",
                "wins": 13,
                "losses": 42,
                "ties": 1
              },
              {
                "type": "xWinLoss",
                "wins": 42,
                "losses": 54,
                "luck": 5
              }
            ],
            "lastTen": {
              "wins": 7,
              "losses": 3,
              "ties": 0
            },
            "gamesBack": "13.0"
          },
          "home": {
            "gamesPlayed": 47,
            "wins": 24,
            "losses": 22,
            "ties": 1,
            "runsScored": 132,
            "runsAllowed": 137,
            "runDifferential": -5,
            "wlt": "WLLLLLLLWWLWWLWWWLLWLWTLWLWLLLWWWWWLWWLLLLWWWWW",
            "streak": "W5",
            "splitRecords": [
              {
                "type": "left",
                "wins": 13,
                "losses": 13,
                "ties": 1
              },
              {
                "type": "right",
                "wins": 11,
                "losses": 9,
                "ties": 0
              },
              {
                "type": "oneRun",
                "wins": 11,
                "losses": 3
              },
              {
                "type": "shutout",
                "pitching": 7,
                "batting": 7,
                "ties": 0
              },
              {
                "type": "doubleDigitRuns",
                "scored": 1,
                "allowed": 1
              },
              {
                "type": "extraInning",
                "wins": 4,
                "losses": 0,
                "ties": 1
              },
              {
                "type": "walkoff",
                "wins": 6,
                "losses": 0
              },
              {
                "type": "comeback",
                "wins": 8,
                "losses": 4,
                "ties": 0
              },
              {
                "type": "firstRunScored",
                "wins": 16,
                "losses": 4,
                "ties": 0
              },
              {
                "type": "firstRunAllowed",
                "wins": 8,
                "losses": 18,
                "ties": 1
              },
              {
                "type": "xWinLoss",
                "wins": 22,
                "losses": 24,
                "luck": 2
              }
            ],
            "lastTen": {
              "wins": 6,
              "losses": 4,
              "ties": 0
            }
          },
          "road": {
            "gamesPlayed": 51,
            "wins": 23,
            "losses": 27,
            "ties": 1,
            "runsScored": 150,
            "runsAllowed": 189,
            "runDifferential": -39,
            "wlt": "LWLWLWWWWWWLLLWLLLLWLLWLWWLLTWWWLLLLWLLLWWLWLWWWLLL",
            "streak": "L3",
            "splitRecords": [
              {
                "type": "left",
                "wins": 5,
                "losses": 13,
                "ties": 0
              },
              {
                "type": "right",
                "wins": 18,
                "losses": 14,
                "ties": 1
              },
              {
                "type": "oneRun",
                "wins": 7,
                "losses": 8
              },
              {
                "type": "shutout",
                "pitching": 4,
                "batting": 6,
                "ties": 0
              },
              {
                "type": "doubleDigitRuns",
                "scored": 0,
                "allowed": 2
              },
              {
                "type": "extraInning",
                "wins": 3,
                "losses": 2,
                "ties": 1
              },
              {
                "type": "walkoff",
                "wins": 0,
                "losses": 4
              },
              {
                "type": "comeback",
                "wins": 6,
                "losses": 4,
                "ties": 1
              },
              {
                "type": "firstRunScored",
                "wins": 18,
                "losses": 3,
                "ties": 1
              },
              {
                "type": "firstRunAllowed",
                "wins": 5,
                "losses": 24,
                "ties": 0
              },
              {
                "type": "xWinLoss",
                "wins": 20,
                "losses": 30,
                "luck": 3
              }
            ],
            "lastTen": {
              "wins": 5,
              "losses": 5,
              "ties": 0
            }
          },
          "lastUpdated": "2025-08-07"
        },
        {
          "teamName": "Lions",
          "league": "Pacific",
          "wins": 45,
          "losses": 52,
          "ties": 2,
          "pct": ".464",
          "overall": {
            "gamesPlayed": 99,
            "wins": 45,
            "losses": 52,
            "ties": 2,
            "runsScored": 256,
            "runsAllowed": 287,
            "runDifferential": -31,
            "wlt": "LLLLWWLLWLWWLWWWWLLLLWWWWWWLLLWWWWLWLWWLWLLWWLWLLWWWLLLLWWWLWWWLWLLWLWLLLWLLLLWTWLLLWLLLLLWLLWTLLLW",
            "streak": "W1",
            "splitRecords": [
              {
                "type": "left",
                "wins": 15,
                "losses": 18,
                "ties": 0
              },
              {
                "type": "right",
                "wins": 30,
                "losses": 34,
                "ties": 2
              },
              {
                "type": "oneRun",
                "wins": 20,
                "losses": 13
              },
              {
                "type": "shutout",
                "pitching": 18,
                "batting": 11,
                "ties": 0
              },
              {
                "type": "doubleDigitRuns",
                "scored": 2,
                "allowed": 4
              },
              {
                "type": "extraInning",
                "wins": 4,
                "losses": 7,
                "ties": 2
              },
              {
                "type": "walkoff",
                "wins": 5,
                "losses": 4
              },
              {
                "type": "comeback",
                "wins": 10,
                "losses": 23,
                "ties": 1
              },
              {
                "type": "firstRunScored",
                "wins": 36,
                "losses": 21,
                "ties": 1
              },
              {
                "type": "firstRunAllowed",
                "wins": 9,
                "losses": 31,
                "ties": 1
              },
              {
                "type": "xWinLoss",
                "wins": 43,
                "losses": 54,
                "luck": 2
              }
            ],
            "lastTen": {
              "wins": 3,
              "losses": 6,
              "ties": 1
            },
            "gamesBack": "15.5"
          },
          "home": {
            "gamesPlayed": 52,
            "wins": 26,
            "losses": 25,
            "ties": 1,
            "runsScored": 141,
            "runsAllowed": 142,
            "runDifferential": -1,
            "wlt": "LLLLWWWLLWWWWWLLWWWWWWLLWLWWLWWWLWWLWLLLLLWLLWLLLWTL",
            "streak": "L1",
            "splitRecords": [
              {
                "type": "left",
                "wins": 8,
                "losses": 6,
                "ties": 0
              },
              {
                "type": "right",
                "wins": 18,
                "losses": 19,
                "ties": 1
              },
              {
                "type": "oneRun",
                "wins": 12,
                "losses": 5
              },
              {
                "type": "shutout",
                "pitching": 10,
                "batting": 6,
                "ties": 0
              },
              {
                "type": "doubleDigitRuns",
                "scored": 2,
                "allowed": 2
              },
              {
                "type": "extraInning",
                "wins": 3,
                "losses": 4,
                "ties": 1
              },
              {
                "type": "walkoff",
                "wins": 5,
                "losses": 0
              },
              {
                "type": "comeback",
                "wins": 7,
                "losses": 9,
                "ties": 1
              },
              {
                "type": "firstRunScored",
                "wins": 19,
                "losses": 9,
                "ties": 1
              },
              {
                "type": "firstRunAllowed",
                "wins": 7,
                "losses": 16,
                "ties": 0
              },
              {
                "type": "xWinLoss",
                "wins": 25,
                "losses": 26,
                "luck": 1
              }
            ],
            "lastTen": {
              "wins": 3,
              "losses": 6,
              "ties": 1
            }
          },
          "road": {
            "gamesPlayed": 47,
            "wins": 19,
            "losses": 27,
            "ties": 1,
            "runsScored": 115,
            "runsAllowed": 145,
            "runDifferential": -30,
            "wlt": "LWWLLWWLWWLLWLLWLWLLWWLWLLLWLWLLWWLLTWLLLWLLLLW",
            "streak": "W1",
            "splitRecords": [
              {
                "type": "left",
                "wins": 7,
                "losses": 12,
                "ties": 0
              },
              {
                "type": "right",
                "wins": 12,
                "losses": 15,
                "ties": 1
              },
              {
                "type": "oneRun",
                "wins": 8,
                "losses": 8
              },
              {
                "type": "shutout",
                "pitching": 8,
                "batting": 5,
                "ties": 0
              },
              {
                "type": "doubleDigitRuns",
                "scored": 0,
                "allowed": 2
              },
              {
                "type": "extraInning",
                "wins": 1,
                "losses": 3,
                "ties": 1
              },
              {
                "type": "walkoff",
                "wins": 0,
                "losses": 4
              },
              {
                "type": "comeback",
                "wins": 3,
                "losses": 14,
                "ties": 0
              },
              {
                "type": "firstRunScored",
                "wins": 17,
                "losses": 12,
                "ties": 0
              },
              {
                "type": "firstRunAllowed",
                "wins": 2,
                "losses": 15,
                "ties": 1
              },
              {
                "type": "xWinLoss",
                "wins": 18,
                "losses": 28,
                "luck": 1
              }
            ],
            "lastTen": {
              "wins": 3,
              "losses": 7,
              "ties": 0
            }
          },
          "lastUpdated": "2025-08-07"
        },
        {
          "teamName": "Marines",
          "league": "Pacific",
          "wins": 37,
          "losses": 57,
          "ties": 3,
          "pct": ".394",
          "overall": {
            "gamesPlayed": 97,
            "wins": 37,
            "losses": 57,
            "ties": 3,
            "runsScored": 287,
            "runsAllowed": 384,
            "runDifferential": -97,
            "wlt": "WWWLLLWLWLLLLWWLLWWWLWLLLLLLWLLLLLWLWLLWWLLWLLLLWWLLLWLWWLWWLLWLWWLWLLWLWLLLTLWLLTLWWWLWLLLLTWWLL",
            "streak": "L2",
            "splitRecords": [
              {
                "type": "left",
                "wins": 14,
                "losses": 27,
                "ties": 2
              },
              {
                "type": "right",
                "wins": 23,
                "losses": 30,
                "ties": 1
              },
              {
                "type": "oneRun",
                "wins": 12,
                "losses": 21
              },
              {
                "type": "shutout",
                "pitching": 5,
                "batting": 19,
                "ties": 0
              },
              {
                "type": "doubleDigitRuns",
                "scored": 1,
                "allowed": 5
              },
              {
                "type": "extraInning",
                "wins": 5,
                "losses": 4,
                "ties": 2
              },
              {
                "type": "walkoff",
                "wins": 5,
                "losses": 7
              },
              {
                "type": "comeback",
                "wins": 16,
                "losses": 16,
                "ties": 1
              },
              {
                "type": "firstRunScored",
                "wins": 22,
                "losses": 11,
                "ties": 2
              },
              {
                "type": "firstRunAllowed",
                "wins": 15,
                "losses": 46,
                "ties": 1
              },
              {
                "type": "xWinLoss",
                "wins": 35,
                "losses": 59,
                "luck": 2
              }
            ],
            "lastTen": {
              "wins": 3,
              "losses": 6,
              "ties": 1
            },
            "gamesBack": "22.0"
          },
          "home": {
            "gamesPlayed": 47,
            "wins": 21,
            "losses": 25,
            "ties": 1,
            "runsScored": 151,
            "runsAllowed": 185,
            "runDifferential": -34,
            "wlt": "LLLWLLLLWWWLWLWWLLWLWWWLWWLWWLWLLLTLWLWWWLLLWLL",
            "streak": "L2",
            "splitRecords": [
              {
                "type": "left",
                "wins": 8,
                "losses": 11,
                "ties": 1
              },
              {
                "type": "right",
                "wins": 13,
                "losses": 14,
                "ties": 0
              },
              {
                "type": "oneRun",
                "wins": 7,
                "losses": 10
              },
              {
                "type": "shutout",
                "pitching": 5,
                "batting": 5,
                "ties": 0
              },
              {
                "type": "doubleDigitRuns",
                "scored": 0,
                "allowed": 2
              },
              {
                "type": "extraInning",
                "wins": 3,
                "losses": 4,
                "ties": 1
              },
              {
                "type": "walkoff",
                "wins": 5,
                "losses": 0
              },
              {
                "type": "comeback",
                "wins": 9,
                "losses": 8,
                "ties": 0
              },
              {
                "type": "firstRunScored",
                "wins": 13,
                "losses": 6,
                "ties": 1
              },
              {
                "type": "firstRunAllowed",
                "wins": 8,
                "losses": 19,
                "ties": 0
              },
              {
                "type": "xWinLoss",
                "wins": 19,
                "losses": 27,
                "luck": 2
              }
            ],
            "lastTen": {
              "wins": 4,
              "losses": 6,
              "ties": 0
            }
          },
          "road": {
            "gamesPlayed": 50,
            "wins": 16,
            "losses": 32,
            "ties": 2,
            "runsScored": 136,
            "runsAllowed": 199,
            "runDifferential": -63,
            "wlt": "WWWWLWLLWLWLLLLLLLLLLWLLWLLLLLLWLLWLWLWLWLLLTLWLTW",
            "streak": "W1",
            "splitRecords": [
              {
                "type": "left",
                "wins": 6,
                "losses": 16,
                "ties": 1
              },
              {
                "type": "right",
                "wins": 10,
                "losses": 16,
                "ties": 1
              },
              {
                "type": "oneRun",
                "wins": 5,
                "losses": 11
              },
              {
                "type": "shutout",
                "pitching": 0,
                "batting": 14,
                "ties": 0
              },
              {
                "type": "doubleDigitRuns",
                "scored": 1,
                "allowed": 3
              },
              {
                "type": "extraInning",
                "wins": 2,
                "losses": 0,
                "ties": 1
              },
              {
                "type": "walkoff",
                "wins": 0,
                "losses": 7
              },
              {
                "type": "comeback",
                "wins": 7,
                "losses": 8,
                "ties": 1
              },
              {
                "type": "firstRunScored",
                "wins": 9,
                "losses": 5,
                "ties": 1
              },
              {
                "type": "firstRunAllowed",
                "wins": 7,
                "losses": 27,
                "ties": 1
              },
              {
                "type": "xWinLoss",
                "wins": 16,
                "losses": 32,
                "luck": 0
              }
            ],
            "lastTen": {
              "wins": 3,
              "losses": 5,
              "ties": 2
            }
          },
          "lastUpdated": "2025-08-07"
        }
      ]
    }
  ]
}